<?xml version="1.0" encoding="UTF-8"?>

<FindBugsFilter>
  <LastVersion value="-1" relOp="NEQ"/>
  <!-- The following have not yet been investigated -->
  <!-- TODO(yanivi): investigate them -->
  <And>
    <Bug pattern="EQ_DOESNT_OVERRIDE_EQUALS"/>
  </And>
  <!-- The following are known to be bugs and should be fixed -->
  <!-- The following are known to not be bugs and should not be fixed -->
  <And>
    <Bug pattern="EI_EXPOSE_REP,EI_EXPOSE_REP2"/> 
    <Class name="com.google.api.client.auth.jsontoken.JsonWebSignature"/>
  </And>
  <!-- TODO(ngmiceli): remove this once upgraded to newer FindBugs -->
  <And>
    <Bug pattern="NP_ALWAYS_NULL"/>
  </And>
  <And>
    <Class name="com.google.api.client.auth.oauth2.TokenRequest"/>
    <Bug pattern="CN_IDIOM_NO_SUPER_CALL"/>
  </And>
</FindBugsFilter>
